Metadata-Version: 2.1
Name: crossasr
Version: 0.1.2
Summary: CrossASR++ A Modular Differential Testing Framework for Automatic Speech Recognition
Home-page: https://github.com/soarsmu/CrossASRplus
Author: Muhammad Hilmi Asyrofi
Author-email: mhilmia@smu.edu.sg
License: MIT
Download-URL: https://github.com/soarsmu/CrossASRplus/archive/refs/tags/v0.1.2.tar.gz
Keywords: crossasr,differential testing,cross-referencing,ASR
Platform: UNKNOWN
Classifier: Development Status :: 3 - Alpha
Classifier: Intended Audience :: Developers
Classifier: Topic :: Software Development :: Build Tools
Classifier: License :: OSI Approved :: MIT License
Classifier: Programming Language :: Python :: 3
Classifier: Programming Language :: Python :: 3.4
Classifier: Programming Language :: Python :: 3.5
Classifier: Programming Language :: Python :: 3.6
Classifier: Programming Language :: Python :: 3.7
Classifier: Programming Language :: Python :: 3.8
